odoo10_addon_product_multi_category-10.0.1.0.0-py2.7-nspkg.pth
odoo/addons/product_multi_category/README.rst
odoo/addons/product_multi_category/__init__.py
odoo/addons/product_multi_category/__manifest__.py
odoo/addons/product_multi_category/i18n/ca.po
odoo/addons/product_multi_category/i18n/es.po
odoo/addons/product_multi_category/i18n/fr.po
odoo/addons/product_multi_category/i18n/fr_BE.po
odoo/addons/product_multi_category/i18n/product_m2mcategories.pot
odoo/addons/product_multi_category/i18n/sv.po
odoo/addons/product_multi_category/i18n/tr.po
odoo/addons/product_multi_category/models/__init__.py
odoo/addons/product_multi_category/models/product.py
odoo/addons/product_multi_category/static/description/icon.png
odoo/addons/product_multi_category/views/product_view.xml
odoo10_addon_product_multi_category-10.0.1.0.0.dist-info/DESCRIPTION.rst
odoo10_addon_product_multi_category-10.0.1.0.0.dist-info/METADATA
odoo10_addon_product_multi_category-10.0.1.0.0.dist-info/RECORD
odoo10_addon_product_multi_category-10.0.1.0.0.dist-info/WHEEL
odoo10_addon_product_multi_category-10.0.1.0.0.dist-info/metadata.json
odoo10_addon_product_multi_category-10.0.1.0.0.dist-info/namespace_packages.txt
odoo10_addon_product_multi_category-10.0.1.0.0.dist-info/top_level.txt
